{"type":"FeatureCollection","features":[{"type":"Feature","id":"node/1543880944","properties":{"description":"Phare : Plate-forme supérieure : Axe et base - Point vu en place en 1986","ele":"18.28","man_made":"lighthouse","name":"Phare de l'île Harbour","note":"Ne pas déplacer ce point, cf. - Do not move this node, see - http://wiki.openstreetmap.org/wiki/WikiProject_France/Repères_Géodésiques#Permanence_des_rep.C3.A8res","ref":"22000I - A","seamark:light:1:character":"Fl","seamark:light:1:colour":"red","seamark:light:1:height":"16","seamark:light:1:period":"4","seamark:light:1:range":"6","seamark:light:1:sector_end":"133","seamark:light:1:sector_start":"11","seamark:light:2:character":"Fl","seamark:light:2:colour":"green","seamark:light:2:height":"16","seamark:light:2:period":"4","seamark:light:2:range":"6","seamark:light:2:sector_end":"270","seamark:light:2:sector_start":"133","seamark:light:3:character":"Fl","seamark:light:3:colour":"red","seamark:light:3:height":"16","seamark:light:3:period":"4","seamark:light:3:range":"6","seamark:light:3:sector_end":"306","seamark:light:3:sector_start":"270","seamark:light:4:character":"Fl","seamark:light:4:colour":"green","seamark:light:4:height":"16","seamark:light:4:period":"4","seamark:light:4:range":"6","seamark:light:4:sector_end":"358","seamark:light:4:sector_start":"306","seamark:light:5:character":"Fl","seamark:light:5:colour":"white","seamark:light:5:height":"16","seamark:light:5:period":"4","seamark:light:5:range":"9","seamark:light:5:sector_end":"11","seamark:light:5:sector_start":"358","seamark:light:reference":"A 1714","seamark:type":"light_minor","source":"US NGA Pub. 114. 2011-05-26.;©IGN 2010 dans le cadre de la cartographie réglementaire","url":"http://ancien-geodesie.ign.fr/fiche_point.asp?num_site=22000I&no_ptg=01&numero_f50=0915","id":"node/1543880944"},"geometry":{"type":"Point","coordinates":[-2.8083027,48.6665081]}}]}
